py_exchangeratesapi/__init__.py
py_exchangeratesapi/api.py
py_exchangeratesapi-1.0.1.dist-info/LICENSE
py_exchangeratesapi-1.0.1.dist-info/METADATA
py_exchangeratesapi-1.0.1.dist-info/WHEEL
py_exchangeratesapi-1.0.1.dist-info/top_level.txt
py_exchangeratesapi-1.0.1.dist-info/RECORD
