Metadata-Version: 2.1
Name: py-exchangeratesapi
Version: 1.0.1
Summary: Simple python api wrapper for exchangeratesapi.io
Home-page: https://github.com/bizzyvinci/py-exchangeratesapi
Author: Dastan Abdrakhmanov
Author-email: dastand.climber@gmail.com
Maintainer: Bisola Olasehinde
Maintainer-email: horlasehinde@gmail.com
License: UNKNOWN
Platform: UNKNOWN
Classifier: Programming Language :: Python :: 3
Classifier: License :: OSI Approved :: MIT License
Classifier: Operating System :: OS Independent
Requires-Python: >=3
